vertex_ai_huggingface_inference_toolkit/__init__.py
vertex_ai_huggingface_inference_toolkit/diffusers.py
vertex_ai_huggingface_inference_toolkit/diffusers_utils.py
vertex_ai_huggingface_inference_toolkit/model.py
vertex_ai_huggingface_inference_toolkit/py.typed
vertex_ai_huggingface_inference_toolkit/transformers.py
vertex_ai_huggingface_inference_toolkit/transformers_utils.py
vertex_ai_huggingface_inference_toolkit/_internal/diffusers/dockerfiles/Dockerfile.cpu
vertex_ai_huggingface_inference_toolkit/_internal/diffusers/dockerfiles/Dockerfile.gpu
vertex_ai_huggingface_inference_toolkit/_internal/transformers/dockerfiles/Dockerfile.cpu
vertex_ai_huggingface_inference_toolkit/_internal/transformers/dockerfiles/Dockerfile.gpu
vertex_ai_huggingface_inference_toolkit/_internal/transformers/schemas/text-generation/input.yaml
vertex_ai_huggingface_inference_toolkit/_internal/transformers/schemas/text-generation/output.yaml
vertex_ai_huggingface_inference_toolkit/_internal/transformers/schemas/zero-shot-classification/input.yaml
vertex_ai_huggingface_inference_toolkit/_internal/transformers/schemas/zero-shot-classification/output.yaml
vertex_ai_huggingface_inference_toolkit/handler/__init__.py
vertex_ai_huggingface_inference_toolkit/handler/custom_handler.py
vertex_ai_huggingface_inference_toolkit/predictors/__init__.py
vertex_ai_huggingface_inference_toolkit/predictors/diffusers.py
vertex_ai_huggingface_inference_toolkit/predictors/transformers.py
vertex_ai_huggingface_inference_toolkit/server/__init__.py
vertex_ai_huggingface_inference_toolkit/server/custom_serving.py
vertex_ai_huggingface_inference_toolkit/utils/__init__.py
vertex_ai_huggingface_inference_toolkit/utils/cache.py
vertex_ai_huggingface_inference_toolkit/utils/device.py
vertex_ai_huggingface_inference_toolkit/utils/docker.py
vertex_ai_huggingface_inference_toolkit/utils/huggingface.py
vertex_ai_huggingface_inference_toolkit/utils/logging.py
vertex_ai_huggingface_inference_toolkit/utils/gcloud/__init__.py
vertex_ai_huggingface_inference_toolkit-0.0.2.dist-info/METADATA
vertex_ai_huggingface_inference_toolkit-0.0.2.dist-info/WHEEL
vertex_ai_huggingface_inference_toolkit-0.0.2.dist-info/licenses/LICENSE
vertex_ai_huggingface_inference_toolkit-0.0.2.dist-info/RECORD
